README.md
setup.py
IVAOWrapper.egg-info/PKG-INFO
IVAOWrapper.egg-info/SOURCES.txt
IVAOWrapper.egg-info/dependency_links.txt
IVAOWrapper.egg-info/requires.txt
IVAOWrapper.egg-info/top_level.txt
ivao/__init__.py
ivao/atc.py
ivao/client.py
ivao/parser.py
ivao/pilot.py
ivao/server.py