Metadata-Version: 2.1
Name: IVAOWrapper
Version: 0.1.2
Summary: Light Python 3 Wrapper for IVAO Network
Home-page: https://github.com/Tchekda/IVAOWrapper
Author: Tchekda
Author-email: contact@tchekda.fr
License: UNKNOWN
Project-URL: Documentation, https://tchekda.github.io/IVAOWrapper
Project-URL: Source Code, https://github.com/Tchekda/IVAOWrapper
Platform: UNKNOWN
Classifier: Programming Language :: Python :: 3
Classifier: Programming Language :: Python :: 3.4
Classifier: Programming Language :: Python :: 3.5
Classifier: Programming Language :: Python :: 3.6
Classifier: Programming Language :: Python :: 3.7
Classifier: Programming Language :: Python :: 3.8
Classifier: License :: OSI Approved :: MIT License
Classifier: Operating System :: OS Independent
Classifier: Intended Audience :: Developers
Classifier: Intended Audience :: System Administrators
Requires-Python: >=3.4
